trainable_initial_state_rnn/__init__.py
trainable_initial_state_rnn/_trainable_initial_state_rnn.py
trainable_initial_state_rnn-0.0.3.dist-info/LICENSE
trainable_initial_state_rnn-0.0.3.dist-info/METADATA
trainable_initial_state_rnn-0.0.3.dist-info/WHEEL
trainable_initial_state_rnn-0.0.3.dist-info/top_level.txt
trainable_initial_state_rnn-0.0.3.dist-info/RECORD
